MANIFEST.in
Makefile
README.md
requirements_dev.txt
setup.py
tox.ini
crawlers/__init__.py
crawlers/test.py
ioweb/__init__.py
ioweb/cli.py
ioweb/control.py
ioweb/crawler.py
ioweb/data.py
ioweb/error.py
ioweb/error_logger.py
ioweb/gevent_util.py
ioweb/logging.py
ioweb/mongodb.py
ioweb/network_service.py
ioweb/proxylist.py
ioweb/request.py
ioweb/response.py
ioweb/session.py
ioweb/stat.py
ioweb/task_generator.py
ioweb/transport.py
ioweb/urllib3_custom.py
ioweb/util.py
ioweb.egg-info/PKG-INFO
ioweb.egg-info/SOURCES.txt
ioweb.egg-info/dependency_links.txt
ioweb.egg-info/entry_points.txt
ioweb.egg-info/requires.txt
ioweb.egg-info/top_level.txt
ioweb_gevent/__init__.py
ioweb_gevent/cli.py
test/test_base_request.py
test/test_callback_request.py
test/test_realworld.py
test/test_request.py
test/test_resolve.py